MANIFEST.in
README.rst
setup.py
dashmat/__init__.py
dashmat/actions.py
dashmat/collector.py
dashmat/datastore.py
dashmat/errors.py
dashmat/executor.py
dashmat/formatter.py
dashmat/scheduler.py
dashmat.egg-info/PKG-INFO
dashmat.egg-info/SOURCES.txt
dashmat.egg-info/dependency_links.txt
dashmat.egg-info/entry_points.txt
dashmat.egg-info/pbr.json
dashmat.egg-info/requires.txt
dashmat.egg-info/top_level.txt
dashmat/core_modules/__init__.py
dashmat/core_modules/base.py
dashmat/core_modules/amazon_base/__init__.py
dashmat/core_modules/amazon_base/main.py
dashmat/core_modules/amazon_base/server.py
dashmat/core_modules/bootstrap/__init__.py
dashmat/core_modules/bootstrap/main.py
dashmat/core_modules/bootstrap/static/bootstrap-theme.min.css
dashmat/core_modules/bootstrap/static/bootstrap.css
dashmat/core_modules/components/__init__.py
dashmat/core_modules/components/main.py
dashmat/core_modules/components/server.py
dashmat/core_modules/components/static/react/BarChart.jsx
dashmat/core_modules/components/static/react/Number.css
dashmat/core_modules/components/static/react/Number.jsx
dashmat/core_modules/components/static/react/WidgetBox.jsx
dashmat/core_modules/components/static/react/main.jsx
dashmat/core_modules/index/__init__.py
dashmat/core_modules/index/main.py
dashmat/core_modules/index/static/react/Index.css
dashmat/core_modules/index/static/react/main.jsx
dashmat/core_modules/splunk/__init__.py
dashmat/core_modules/splunk/main.py
dashmat/core_modules/splunk/splunk-sdk-1.3.0/PKG-INFO
dashmat/core_modules/splunk/splunk-sdk-1.3.0/setup.py
dashmat/core_modules/splunk/splunk-sdk-1.3.0/splunklib/__init__.py
dashmat/core_modules/splunk/splunk-sdk-1.3.0/splunklib/binding.py
dashmat/core_modules/splunk/splunk-sdk-1.3.0/splunklib/client.py
dashmat/core_modules/splunk/splunk-sdk-1.3.0/splunklib/data.py
dashmat/core_modules/splunk/splunk-sdk-1.3.0/splunklib/ordereddict.py
dashmat/core_modules/splunk/splunk-sdk-1.3.0/splunklib/results.py
dashmat/core_modules/splunk/splunk-sdk-1.3.0/splunklib/modularinput/__init__.py
dashmat/core_modules/splunk/splunk-sdk-1.3.0/splunklib/modularinput/argument.py
dashmat/core_modules/splunk/splunk-sdk-1.3.0/splunklib/modularinput/event.py
