Metadata-Version: 1.0
Name: dashmat
Version: 0.2.8
Summary: Application that reads yaml and serves up a pretty dashboard
Home-page: https://github.com/realestate-com-au/dashmat
Author: Stephen Moore
Author-email: stephen.moore@rea-group.com
License: MIT
Keywords: dashboard
Platform: UNKNOWN
